sdiff.py
srt_timer-0.2.data/scripts/srt_timer.py
srt_timer-0.2.dist-info/DESCRIPTION.rst
srt_timer-0.2.dist-info/METADATA
srt_timer-0.2.dist-info/RECORD
srt_timer-0.2.dist-info/WHEEL
srt_timer-0.2.dist-info/entry_points.txt
srt_timer-0.2.dist-info/metadata.json
srt_timer-0.2.dist-info/top_level.txt
