Metadata-Version: 2.0
Name: srt-timer
Version: 0.2
Summary: Simple script for saving difference of two subtitle timings. You can than easily convert subtitle from one timing to another.
Home-page: https://github.com/Thyrst/srt-timer
Author: Thyrst
Author-email: thyrst@seznam.cz
License: MIT
Download-URL: https://github.com/Thyrst/srt-timer/archive/0.2.tar.gz
Keywords: srt subtitles timing
Platform: UNKNOWN
Classifier: Development Status :: 5 - Production/Stable
Classifier: Environment :: Console
Classifier: Intended Audience :: End Users/Desktop
Classifier: License :: OSI Approved :: MIT License
Classifier: Natural Language :: English
Classifier: Topic :: Text Processing
Classifier: Programming Language :: Python :: 3.6
Requires-Dist: srt
